Metadata-Version: 2.1
Name: ekhusainov-cv-football-task-a
Version: 0.1.12
Summary: Test exercise. CV. Classification.
Author: Khusainov Eldar
Author-email: xluttiy@gmail.com
License: MIT
Platform: UNKNOWN
